codexcollector/__init__.py
codexcollector/codex_exceptions.py
codexcollector/codexcollector.py
codexcollector-0.2.0.dist-info/METADATA
codexcollector-0.2.0.dist-info/WHEEL
codexcollector-0.2.0.dist-info/licenses/LICENSE
codexcollector-0.2.0.dist-info/RECORD
