Metadata-Version: 2.4
Name: codexcollector
Version: 0.2.0
Summary: A wrapper for common Python packages to build a text corpus with a single line of code.
Project-URL: Homepage, https://github.com/NotAndroid37/codexcollector
Project-URL: Repository, https://github.com/NotAndroid37/codexcollector
Project-URL: Issues, https://github.com/NotAndroid37/codexcollector/issues
Project-URL: Documentation, https://github.com/NotAndroid37/codexcollector#readme
Author: NotAndroid37
License: MIT
License-File: LICENSE
Keywords: NLP,corpus building,document extraction,document parsing,docx,natural language processing,pdf,text extraction,text processing,web scraping
Classifier: Development Status :: 4 - Beta
Classifier: Intended Audience :: Developers
Classifier: Intended Audience :: Science/Research
Classifier: License :: OSI Approved :: MIT License
Classifier: Operating System :: OS Independent
Classifier: Programming Language :: Python :: 3
Classifier: Programming Language :: Python :: 3.10
Classifier: Programming Language :: Python :: 3.11
Classifier: Programming Language :: Python :: 3.12
Classifier: Programming Language :: Python :: 3.13
Classifier: Topic :: Software Development :: Libraries :: Python Modules
Classifier: Topic :: Text Processing
Classifier: Topic :: Text Processing :: Linguistic
Requires-Python: >=3.10
Requires-Dist: beautifulsoup4>=4.12.0
Requires-Dist: chardet>=5.2.0
Requires-Dist: docx2txt>=0.9
Requires-Dist: html2text>=2025.4.15
Requires-Dist: pandas>=2.2.3
Requires-Dist: pypdf>=5.1.0
Requires-Dist: python-docx>=1.1.0
Requires-Dist: python-pptx>=1.0.2
Requires-Dist: requests>=2.32.0
